{
  "$schema": "https://ladysnake.org/wiki/blabber/dialogue.schema.json",
  "start_at": "dial0",
  "unskippable": true,
  "title": "Skull Haven",
  "layout": {
    "type": "blabber:rpg"
  },
  "illustrations": {
    "priest": [
      {
        "type": "blabber:texture",
        "texture": "valormobs:textures/blabber/priest.png",
        "anchor": "before_main_text",
        "x": 0,
        "y": -160,
        "width": 150,
        "height": 150
      }
    ]
  },
  "states": {
    "dial0": {
      "text": "<typewriter>Welcome to this world!",
      "illustrations": [
        "priest"
      ],
      "choices": [
        { "text": "Where am I..?", "next": "dial2" }
      ]
    },
    "dial2": {
      "text": "<typewriter>Why, you are in the unforgiving world of Valor!",
      "illustrations": [
        "priest"
      ],
      "choices": [
        { "text": "Okay...", "next": "end" }
      ]
    },
    "end": {
      "type": "end_dialogue"
    }
  }
}














